{
  "type": "vstack",
  "neverRecomputeExistingPartitions": false,
  "optionalDependencies": false,
  "customMeta": {
    "kv": {}
  },
  "redispatchPartitioning": false,
  "maxRunningActivities": 0,
  "inputs": {
    "main": {
      "items": [
        {
          "ref": "data_part2",
          "deps": []
        },
        {
          "ref": "data_part1",
          "deps": []
        }
      ]
    }
  },
  "outputs": {
    "main": {
      "items": [
        {
          "ref": "client_Centric_data1",
          "appendMode": false
        }
      ]
    }
  },
  "versionTag": {
    "versionNumber": 1,
    "lastModifiedBy": {
      "login": "1625462"
    },
    "lastModifiedOn": 1604455149802
  },
  "creationTag": {
    "versionNumber": 0,
    "lastModifiedBy": {
      "login": "1625462"
    },
    "lastModifiedOn": 1604455143185
  },
  "tags": [],
  "customFields": {},
  "checklists": {
    "checklists": []
  }
}